sqlalchemy_boolean_search.py
marvin_sqlalchemy_boolean_search-0.2.2.dist-info/LICENSE.md
marvin_sqlalchemy_boolean_search-0.2.2.dist-info/METADATA
marvin_sqlalchemy_boolean_search-0.2.2.dist-info/WHEEL
marvin_sqlalchemy_boolean_search-0.2.2.dist-info/top_level.txt
marvin_sqlalchemy_boolean_search-0.2.2.dist-info/RECORD
