Metadata-Version: 2.1
Name: marvin-sqlalchemy-boolean-search
Version: 0.2.2
Summary: Boolean search expression parser for SQLAlchemy
Home-page: http://github.com/havok2063/SQLAlchemy-boolean-search
Author: Brian Cherinka
Author-email: bcherinka@stsci.edu
License: BSD 3-Clause License
Project-URL: Repository, http://github.com/havok2063/SQLAlchemy-boolean-search
Keywords: Boolean search Flask SQLAlchemy
Platform: any
Classifier: Development Status :: 4 - Beta
Classifier: Environment :: Web Environment
Classifier: Framework :: Flask
Classifier: Intended Audience :: Developers
Classifier: License :: OSI Approved :: BSD License
Classifier: Natural Language :: English
Classifier: Operating System :: OS Independent
Classifier: Programming Language :: Python
Classifier: Programming Language :: Python :: 2.6
Classifier: Programming Language :: Python :: 2.7
Classifier: Programming Language :: Python :: 3.3
Classifier: Programming Language :: Python :: 3.4
Classifier: Topic :: Database :: Front-Ends
Classifier: Topic :: Software Development :: Libraries :: Python Modules
Requires-Python: >=2.7
Requires-Dist: pyparsing (<3.0,>=2.4)
Requires-Dist: sqlalchemy (<1.4,>=1.3)
Provides-Extra: dev
Requires-Dist: Sphinx (<4.0,>=2.1.0) ; extra == 'dev'
Requires-Dist: ipython (>=7.9.0) ; extra == 'dev'
Requires-Dist: matplotlib (>=3.1.1) ; extra == 'dev'
Requires-Dist: flake8 (>=3.7.9) ; extra == 'dev'
Requires-Dist: doc8 (>=0.8.0) ; extra == 'dev'
Requires-Dist: pytest (>=5.2.2) ; extra == 'dev'
Requires-Dist: pytest-cov (>=2.8.1) ; extra == 'dev'
Requires-Dist: pytest-sugar (>=0.9.2) ; extra == 'dev'
Requires-Dist: isort (>=4.3.21) ; extra == 'dev'
Requires-Dist: codecov (>=2.0.15) ; extra == 'dev'
Requires-Dist: coverage[toml] (>=5.0) ; extra == 'dev'
Requires-Dist: ipdb (>=0.12.3) ; extra == 'dev'
Requires-Dist: invoke (>=1.3.0) ; extra == 'dev'
Requires-Dist: twine (>=3.1.1) ; extra == 'dev'
Requires-Dist: wheel (>=0.33.6) ; extra == 'dev'
Requires-Dist: Flask (>=1.0) ; extra == 'dev'
Requires-Dist: Flask-SQLAlchemy (>=1.0) ; extra == 'dev'
Requires-Dist: pytest-flask (>=0.8.1) ; extra == 'dev'
Provides-Extra: docs
Requires-Dist: Sphinx (<4.0,>=2.1.0) ; extra == 'docs'
